jbot/__init__.py
jbot/adapters/__init__.py
jbot/adapters/cqhttp/__init__.py
jbot/adapters/cqhttp/adapter.py
jbot/adapters/cqhttp/config.py
jbot/adapters/cqhttp/elements.py
jbot/adapters/cqhttp/event_handler.py
jbot/adapters/cqhttp/message_handler.py
jbot/adapters/cqhttp/utils.py
jbot/adapters/mirai/__init__.py
jbot/adapters/mirai/adapter.py
jbot/adapters/mirai/config.py
jbot/adapters/mirai/elements.py
jbot/adapters/mirai/message_handler.py
jbot/adapters/mirai/utils.py
jbot/apis/__init__.py
jbot/apis/adapter.py
jbot/apis/adapter_config.py
jbot/apis/config.py
jbot/apis/contact.py
jbot/apis/element.py
jbot/apis/event.py
jbot/apis/matcher.py
jbot/contact/__init__.py
jbot/contact/friend.py
jbot/contact/group.py
jbot/contact/member.py
jbot/events/__init__.py
jbot/events/message_events.py
jbot/events/notice_events.py
jbot/matchers/__init__.py
jbot/matchers/command_matcher.py
jbot/matchers/keyword_matcher.py
jbot/utils/__init__.py
jbot/utils/listener.py
jbot/utils/listener_manager.py
jbot/utils/logger.py
jbot/utils/matcher_util.py
jbot/utils/message_chain.py
jbot/utils/priority_queue.py
jbot/utils/role.py
jbot-2.1.1.dist-info/LICENSE
jbot-2.1.1.dist-info/METADATA
jbot-2.1.1.dist-info/WHEEL
jbot-2.1.1.dist-info/top_level.txt
jbot-2.1.1.dist-info/RECORD
